work_utils_zxj/__init__.py
work_utils_zxj/comic/__init__.py
work_utils_zxj/comic/split.py
work_utils_zxj/log/__init__.py
work_utils_zxj/log/logger.py
work_utils_zxj/playwright/__init__.py
work_utils_zxj/playwright/spider.py
work_utils_zxj/utils/__init__.py
work_utils_zxj/utils/csv.py
work_utils_zxj-0.1.6.dist-info/licenses/LICENSE
work_utils_zxj-0.1.6.dist-info/METADATA
work_utils_zxj-0.1.6.dist-info/WHEEL
work_utils_zxj-0.1.6.dist-info/RECORD
