Metadata-Version: 2.4
Name: work-utils-zxj
Version: 0.1.6
Summary: work util for self
License-Expression: MIT
License-File: LICENSE
Author: zxj
Author-email: 1114062513@qq.com
Requires-Python: >=3.10,<4.0
Classifier: Programming Language :: Python :: 3
Classifier: Programming Language :: Python :: 3.10
Classifier: Programming Language :: Python :: 3.11
Classifier: Programming Language :: Python :: 3.12
Classifier: Programming Language :: Python :: 3.13
Classifier: Programming Language :: Python :: 3.14
Provides-Extra: all
Provides-Extra: comic
Provides-Extra: log
Provides-Extra: playwright
Provides-Extra: utils
Requires-Dist: pandas (>=2.3.3,<3.0.0) ; extra == "all"
Requires-Dist: pandas (>=2.3.3,<3.0.0) ; extra == "utils"
Requires-Dist: pillow (>=12.0.0,<13.0.0) ; extra == "all"
Requires-Dist: pillow (>=12.0.0,<13.0.0) ; extra == "comic"
Requires-Dist: playwright (==1.51.0) ; extra == "all"
Requires-Dist: playwright (==1.51.0) ; extra == "playwright"
